flowstack/__init__.py
flowstack/agent.py
flowstack/billing.py
flowstack/exceptions.py
flowstack/models.py
flowstack/providers.py
flowstack-1.0.0.dist-info/licenses/LICENSE
flowstack-1.0.0.dist-info/METADATA
flowstack-1.0.0.dist-info/WHEEL
flowstack-1.0.0.dist-info/top_level.txt
flowstack-1.0.0.dist-info/RECORD
